odoo10_addon_website_sale_default_country-10.0.1.0.0-py2.7-nspkg.pth
odoo/addons/website_sale_default_country/README.rst
odoo/addons/website_sale_default_country/__init__.py
odoo/addons/website_sale_default_country/__manifest__.py
odoo/addons/website_sale_default_country/controllers/__init__.py
odoo/addons/website_sale_default_country/controllers/main.py
odoo/addons/website_sale_default_country/static/description/icon.png
odoo10_addon_website_sale_default_country-10.0.1.0.0.dist-info/DESCRIPTION.rst
odoo10_addon_website_sale_default_country-10.0.1.0.0.dist-info/METADATA
odoo10_addon_website_sale_default_country-10.0.1.0.0.dist-info/RECORD
odoo10_addon_website_sale_default_country-10.0.1.0.0.dist-info/WHEEL
odoo10_addon_website_sale_default_country-10.0.1.0.0.dist-info/metadata.json
odoo10_addon_website_sale_default_country-10.0.1.0.0.dist-info/namespace_packages.txt
odoo10_addon_website_sale_default_country-10.0.1.0.0.dist-info/top_level.txt
